filesift/_config/__init__.py
filesift/_config/config.py
filesift/_config/default_config.toml
filesift/_core/__init__.py
filesift/_core/daemon.py
filesift/_core/daemon_main.py
filesift/_core/indexer.py
filesift/_core/query.py
filesift/_core/file_processors/__init__.py
filesift/_core/file_processors/base.py
filesift/_core/file_processors/code_processor.py
filesift/_core/file_processors/config_processor.py
filesift/_core/file_processors/data_processor.py
filesift/_core/file_processors/document_processor.py
filesift/_core/file_processors/image_processor.py
filesift/_core/file_processors/text_processor.py
filesift/api/__init__.py
filesift/cli/__init__.py
filesift/cli/command.py
filesift/cli/daemon_utils.py
filesift-0.1.0.dist-info/licenses/LICENSE
filesift-0.1.0.dist-info/METADATA
filesift-0.1.0.dist-info/WHEEL
filesift-0.1.0.dist-info/entry_points.txt
filesift-0.1.0.dist-info/top_level.txt
filesift-0.1.0.dist-info/RECORD
