Metadata-Version: 2.4
Name: filesift
Version: 0.1.0
Summary: Intelligent file indexing and search system
Author-email: Roshun Sunder <roshun.sunder@gmail.com>
Maintainer-email: Roshun Sunder <roshun.sunder@gmail.com>
License-Expression: MIT
Project-URL: Homepage, https://github.com/roshunsunder/filesift
Keywords: file-search,semantic-search,vector-search,file-indexing,code-search,document-search,faiss,llm,embeddings,natural-language-search
Classifier: Development Status :: 4 - Beta
Classifier: Intended Audience :: Developers
Classifier: Operating System :: OS Independent
Classifier: Programming Language :: Python :: 3
Classifier: Programming Language :: Python :: 3.11
Classifier: Programming Language :: Python :: 3.12
Classifier: Programming Language :: Python :: 3.13
Classifier: Topic :: Software Development :: Libraries :: Python Modules
Classifier: Topic :: System :: Filesystems
Classifier: Topic :: Text Processing :: Indexing
Classifier: Topic :: Utilities
Requires-Python: >=3.11
License-File: LICENSE
Requires-Dist: langchain-community
Requires-Dist: langchain_huggingface
Requires-Dist: faiss-cpu
Requires-Dist: sentence-transformers
Requires-Dist: openai
Requires-Dist: python-dotenv
Requires-Dist: tiktoken
Requires-Dist: rank-bm25
Requires-Dist: click
Requires-Dist: tqdm
Requires-Dist: platformdirs
Requires-Dist: tomli-w
Requires-Dist: PyPDF2
Requires-Dist: python-docx
Requires-Dist: odfpy
Requires-Dist: PyYAML
Provides-Extra: dev
Dynamic: license-file
